ontime/.DS_Store
ontime/__init__.py
ontime/api/__init__.py
ontime/api/modular.py
ontime/context/__init__.py
ontime/context/common/__init__.py
ontime/context/common/anomaly_frequency.py
ontime/context/common/data_quality_detector.py
ontime/context/common/generic_detector.py
ontime/context/common/generic_predictor.py
ontime/context/common/missing_data_detector.py
ontime/context/common/profiler.py
ontime/core/__init__.py
ontime/core/detection/__init__.py
ontime/core/detection/abstract_detector.py
ontime/core/detection/detectors.py
ontime/core/detection/registry/__init__.py
ontime/core/detection/registry/quantile.py
ontime/core/detection/registry/threshold.py
ontime/core/generation/__init__.py
ontime/core/generation/abstract_generator.py
ontime/core/generation/generators.py
ontime/core/generation/registry/__init__.py
ontime/core/generation/registry/constant.py
ontime/core/generation/registry/gaussian.py
ontime/core/generation/registry/holiday.py
ontime/core/generation/registry/linear.py
ontime/core/generation/registry/random_walk.py
ontime/core/generation/registry/sine.py
ontime/core/modelling/__init__.py
ontime/core/modelling/abstract_model.py
ontime/core/modelling/libs/__init__.py
ontime/core/modelling/libs/darts/__init__.py
ontime/core/modelling/libs/darts/darts_forecasting_model.py
ontime/core/modelling/libs/pytorch/__init__.py
ontime/core/modelling/libs/pytorch/abstract_pytorch_model.py
ontime/core/modelling/libs/pytorch/pytorch_forecasting_model.py
ontime/core/modelling/libs/skforecast/__init__.py
ontime/core/modelling/libs/skforecast/forecaster_autoreg.py
ontime/core/modelling/libs/skforecast/forecaster_autoreg_multi_variate.py
ontime/core/modelling/libs/tensorflow/__init__.py
ontime/core/modelling/model.py
ontime/core/modelling/models.py
ontime/core/modelling/registry/__init__.py
ontime/core/modelling/registry/autoencoder.py
ontime/core/modelling/registry/gru.py
ontime/core/modelling/registry/variational_autoencoder.py
ontime/core/plotting/__init__.py
ontime-0.7.0.dist-info/LICENSE
ontime-0.7.0.dist-info/METADATA
ontime-0.7.0.dist-info/WHEEL
ontime-0.7.0.dist-info/RECORD
