Metadata-Version: 2.1
Name: ontime
Version: 0.7.0
Summary: Your library to work with time series
Author: Fred Montet
Author-email: fredmontet@gmail.com
Requires-Python: >=3.10,<3.13
Classifier: Programming Language :: Python :: 3
Classifier: Programming Language :: Python :: 3.10
Classifier: Programming Language :: Python :: 3.11
Classifier: Programming Language :: Python :: 3.12
Requires-Dist: alive-progress (>=3.2.0,<4.0.0)
Requires-Dist: altair (>=5.1.0,<6.0.0)
Requires-Dist: altair-viewer (>=0.4.0,<0.5.0)
Requires-Dist: calmap (>=0.0.11,<0.0.12)
Requires-Dist: catboost (>=1.2,<2.0)
Requires-Dist: darts (>=0.30.0,<0.31.0)
Requires-Dist: ipywidgets (>=8.1.1,<9.0.0)
Requires-Dist: lightning (>=2.2.4,<3.0.0)
Requires-Dist: numpy (>=1.26.4,<2.0.0)
Requires-Dist: periodicity-detection (>=0.1.3,<0.2.0)
Requires-Dist: protobuf (>=4.24.4,<5.0.0)
Requires-Dist: skforecast (>=0.12.0,<0.13.0)
Requires-Dist: tensorflow (>=2.16.1,<3.0.0)
Requires-Dist: torch (>=2.0.0,!=2.0.1,!=2.1.0)
Requires-Dist: vega-datasets (>=0.9.0,<0.10.0)
Requires-Dist: vegafusion-python-embed (>=1.4.1,<2.0.0)
Requires-Dist: vegafusion[embed] (>=1.4.1,<2.0.0)
